aipproto/__init__.py
aipproto/generate.py
aipproto/resource.py
aipproto/resource_config.py
aipproto/_internal/hierarchy.py
aipproto/_internal/method_group.py
aipproto/_internal/options.py
aipproto/_internal/render.py
aipproto/_internal/methods/create_method.py
aipproto/_internal/methods/custom_method.py
aipproto/_internal/methods/delete_method.py
aipproto/_internal/methods/get_method.py
aipproto/_internal/methods/list_method.py
aipproto/_internal/methods/update_method.py
aipproto/_internal/req_res/create_req_res.py
aipproto/_internal/req_res/custom_req_res.py
aipproto/_internal/req_res/delete_req_res.py
aipproto/_internal/req_res/get_req_res.py
aipproto/_internal/req_res/list_req_res.py
aipproto/_internal/req_res/update_req_res.py
aipproto/_internal/templates/proto.jinja
aipproto-0.0.4.dist-info/licenses/LICENSE
aipproto-0.0.4.dist-info/METADATA
aipproto-0.0.4.dist-info/WHEEL
aipproto-0.0.4.dist-info/top_level.txt
aipproto-0.0.4.dist-info/RECORD
