Metadata-Version: 2.4
Name: aipproto
Version: 0.0.4
Summary: AIP proto generator
Author-email: Phil Stahlfeld <phil@stahlfeld.com>
Project-URL: Homepage, https://github.com/philstahlfeld/aipproto
Project-URL: Issues, https://github.com/philstahlfeld/aipproto/issues
Requires-Python: >=3.10
License-File: LICENSE
Requires-Dist: jinja2>=3.0
Provides-Extra: test
Requires-Dist: pytest>=7.0; extra == "test"
Requires-Dist: pytest-cov; extra == "test"
Dynamic: license-file
